WchSpider/__init__.py
WchSpider-1.0.0.dist-info/METADATA
WchSpider-1.0.0.dist-info/WHEEL
WchSpider-1.0.0.dist-info/top_level.txt
WchSpider-1.0.0.dist-info/RECORD
