Metadata-Version: 2.1
Name: WchSpider
Version: 1.0.0
Summary: WchSpider
Home-page: https://github.com/DARK1994/WchSpiders
Author: wch
Author-email: mambaout0803@163.com
License: UNKNOWN
Keywords: pip,requests,aiohttp,spider
Platform: any
Requires-Dist: aiohttp
Requires-Dist: lxml
